AIvoifu/__init__.py
AIvoifu/client_pipeline.py
AIvoifu/tts/tts.py
AIvoifu/tts/tts_base_models/__init__.py
AIvoifu/tts/tts_base_models/khanomtal11/config.json
AIvoifu/tts/tts_base_models/khanomtal11/config_se.json
AIvoifu/tts/tts_base_models/khanomtal11/language_ids.json
AIvoifu/tts/tts_base_models/khanomtal11/nconfig.json
AIvoifu/tts/tts_base_models/khanomtal11/speech.py
AIvoifu/tts/tts_base_models/readme.md
AIvoifu/voice_conversion/RVC/README.md
AIvoifu/voice_conversion/RVC/__init__.py
AIvoifu/voice_conversion/RVC/config.py
AIvoifu/voice_conversion/RVC/infer_pack/attentions.py
AIvoifu/voice_conversion/RVC/infer_pack/commons.py
AIvoifu/voice_conversion/RVC/infer_pack/models.py
AIvoifu/voice_conversion/RVC/infer_pack/models_onnx.py
AIvoifu/voice_conversion/RVC/infer_pack/modules.py
AIvoifu/voice_conversion/RVC/infer_pack/transforms.py
AIvoifu/voice_conversion/RVC/poetry.lock
AIvoifu/voice_conversion/RVC/pyproject.toml
AIvoifu/voice_conversion/RVC/python_inference.py
AIvoifu/voice_conversion/RVC/requirements.txt
AIvoifu/voice_conversion/RVC/vc_infer_pipeline.py
AIvoifu/voice_conversion/config.json
AIvoifu/voice_conversion/vc_inference.py
AIvoifu/voice_conversion/zoo/alice/meta.json
AIvoifu/voice_conversion/zoo/ayaka-jp/meta.json
AIvoifu/voice_conversion/zoo/kazuha-jp/meta.json
AIvoifu/voice_conversion/zoo/readme.md
AIvoifu/voice_conversion/zoo/xiao-jp/meta.json
aivoifu-0.2.9.dist-info/LICENSE
aivoifu-0.2.9.dist-info/METADATA
aivoifu-0.2.9.dist-info/WHEEL
aivoifu-0.2.9.dist-info/RECORD
