Metadata-Version: 2.1
Name: aivoifu
Version: 0.2.9
Summary: Easy and fast AI Waifu voice generation
License: MIT
Author: HRNPH
Author-email: hrnph@protonmail.com
Requires-Python: >=3.10,<4.0
Classifier: License :: OSI Approved :: MIT License
Classifier: Programming Language :: Python :: 3
Classifier: Programming Language :: Python :: 3.10
Classifier: Programming Language :: Python :: 3.11
Classifier: Programming Language :: Python :: 3.12
Requires-Dist: deepspeed (>=0.14.2,<0.15.0)
Requires-Dist: edge-tts (>=6.1.10,<7.0.0)
Requires-Dist: fairseq (>=0.12.2,<0.13.0)
Requires-Dist: faiss-cpu (>=1.7.4,<2.0.0)
Requires-Dist: gtts (>=2.5.0,<3.0.0)
Requires-Dist: librosa (>=0.10.1,<0.11.0)
Requires-Dist: nomkl (>=0.0.3,<0.0.4)
Requires-Dist: optimum (>=1.17.1,<2.0.0)
Requires-Dist: praat-parselmouth (>=0.4.3,<0.5.0)
Requires-Dist: pyworld (>=0.3.4,<0.4.0)
Requires-Dist: scipy (>=1.13.0,<2.0.0)
Requires-Dist: setuptools (>=69.0.3,<70.0.0)
Requires-Dist: soundfile (>=0.12.1,<0.13.0)
Requires-Dist: torch (>=2.1.2,<3.0.0)
Requires-Dist: transformers (>=4.38.2,<5.0.0)
Requires-Dist: wget (>=3.2,<4.0)
